artemis_py/__init__.py
artemis_py/api.py
artemis_py-0.2.4.dist-info/METADATA
artemis_py-0.2.4.dist-info/WHEEL
artemis_py-0.2.4.dist-info/top_level.txt
artemis_py-0.2.4.dist-info/RECORD
