Metadata-Version: 2.1
Name: artemis-py
Version: 0.2.4
Summary: A package to interact with the Artemis API. Visit artemis.xyz for more.
Home-page: https://github.com/MattMaximo/artemis_py
Author: Matt Maximo
Author-email: matt@pioneerdigital.org
Classifier: Programming Language :: Python :: 3
Classifier: License :: OSI Approved :: MIT License
Classifier: Operating System :: OS Independent
Requires-Python: >=3.6
Requires-Dist: pandas
Requires-Dist: requests
